links_extractor.py
links_extractor-0.0.1.dist-info/top_level.txt
links_extractor-0.0.1.dist-info/DESCRIPTION.rst
links_extractor-0.0.1.dist-info/RECORD
links_extractor-0.0.1.dist-info/METADATA
links_extractor-0.0.1.dist-info/WHEEL
links_extractor-0.0.1.dist-info/metadata.json
links_extractor-0.0.1.data/scripts/links_extractor.py
