Metadata-Version: 2.0
Name: links-extractor
Version: 0.0.1
Summary: Extract links from a URL
Home-page: https://github.com/surrealcristian/links_extractor
Author: Cristian Cabrera
Author-email: surrealcristian@gmail.com
License: MIT
Keywords: links extractor url
Platform: UNKNOWN
Classifier: Development Status :: 3 - Alpha
Classifier: Environment :: Console
Classifier: Intended Audience :: Developers
Classifier: Intended Audience :: End Users/Desktop
Classifier: License :: OSI Approved :: MIT License
Classifier: Natural Language :: English
Classifier: Operating System :: POSIX
Classifier: Programming Language :: Python
Classifier: Programming Language :: Python :: 3 :: Only
Classifier: Topic :: Software Development :: Libraries
Classifier: Topic :: Utilities
Classifier: Topic :: Internet :: WWW/HTTP
Requires-Dist: requests (>=2)
Requires-Dist: lxml (>=3)
